{
  "colors": {
    "background": {
      "default": "#222222",
      "yellow": "#BC5A00",
      "magenta": "#750049",
      "blue": "#005C99",
      "red": "#8F1F14",
      "green": "#005555",
      "gray1": "#C3C3C3",
      "gray2": "#9B9B9B",
      "inverted": "#FFFFFF",
      "hover": {
        "default": "#363636",
        "yellow": "#d3770d",
        "magenta": "#A20065",
        "blue": "#0E7EC8",
        "red": "#B33225",
        "green": "#007A7A",
        "gray1": "{base.gray.4000}",
        "gray2": "{base.gray.5500}",
        "inverted": "#222222"
      }
    },
    "label": {
      "default": "#FFFFFF",
      "yellow": "#fff7cc",
      "magenta": "#ffe0ed",
      "blue": "#9ee4ea",
      "red": "#ffaaa2",
      "green": "#a2e8bd",
      "white": "#FFFFFF",
      "inverted": "#222222",
      "inactive": {
        "default": "#9B9B9B",
        "yellow": "#FFA700",
        "magenta": "#FF3FAB",
        "blue": "#00DAF2",
        "red": "#FB5B5B",
        "green": "#85E500",
        "white": "#9B9B9B",
        "inverted": "#727272"
      },
      "highlight": {
        "yellow": "#FFA700",
        "magenta": "#FF3FAB",
        "blue": "#00DAF2",
        "red": "#FF3434",
        "green": "#85E500"
      },
      "link": {
        "default": "#00DAF2",
        "hover": "#8EF4FF",
        "visited": {
          "default": "#FF9CCD",
          "hover": "#ffe0ed"
        }
      }
    },
    "overlay": "linear-gradient(45deg, transparent, #222222 100%)",
    "base": {
      "black": "#222222",
      "white": "#FFFFFF",
      "yellow": {
        "1": "#fff7cc",
        "2": "#FFD484",
        "3": "#FFA700",
        "4": "#d3770d",
        "5": "#BC5A00",
        "6": "#4f1800"
      },
      "red": {
        "1": "#FEFFCB",
        "2": "#ffaaa2",
        "3": "#FB5B5B",
        "4": "#FF3434",
        "5": "#B33225",
        "6": "#8F1F14"
      },
      "blue": {
        "1": "#9ee4ea",
        "2": "#8EF4FF",
        "3": "#00DAF2",
        "4": "#0E7EC8",
        "5": "#005C99",
        "6": "#002944"
      },
      "green": {
        "1": "#a2e8bd",
        "2": "#C7F881",
        "3": "#85E500",
        "4": "#007A7A",
        "5": "#005555",
        "6": "#001C1C"
      },
      "magenta": {
        "1": "#ffe0ed",
        "2": "#FF9CCD",
        "3": "#FF3FAB",
        "4": "#A20065",
        "5": "#750049",
        "6": "#47002c"
      },
      "gray": {
        "1": "#FFFFFF",
        "2": "#EBEBEB",
        "3": "#D7D7D7",
        "4": "#C3C3C3",
        "5": "#AFAFAF",
        "6": "#9B9B9B",
        "7": "#868686",
        "8": "#727272",
        "9": "#5E5E5E",
        "10": "#4A4A4A",
        "11": "#363636",
        "12": "#222222"
      }
    }
  },
  "borders": {
    "focus": {
      "default": "2px solid #FFFFFF",
      "link": {
        "default": "4.5px solid #00DAF2",
        "hover": "4.5px solid #8EF4FF",
        "visited": {
          "default": "4.5px solid #FF9CCD",
          "hover": "4.5px solid #ffe0ed"
        }
      }
    }
  },
  "borderWidths": {
    "strokeWeight": {
      "1": "1.5px",
      "2": "3px",
      "3": "4.5px",
      "4": "6px",
      "5": "7.5px",
      "6": "9px"
    }
  },
  "boxShadows": {
    "border": {
      "focus": {
        "default": "inset 0px 0px 0px 4.5px #222222,inset 0px 0px 0px 9px #FFFFFF",
        "green": "inset 0px 0px 0px 4.5px #005555,inset 0px 0px 0px 9px #a2e8bd",
        "blue": "inset 0px 0px 0px 4.5px #005C99,inset 0px 0px 0px 9px #9ee4ea",
        "red": "inset 0px 0px 0px 4.5px #8F1F14,inset 0px 0px 0px 9px #ffaaa2",
        "yellow": "inset 0px 0px 0px 4.5px #BC5A00,inset 0px 0px 0px 9px #fff7cc",
        "magenta": "inset 0px 0px 0px 4.5px #750049,inset 0px 0px 0px 9px #ffe0ed",
        "gray1": "inset 0px 0px 0px 4.5px #C3C3C3,inset 0px 0px 0px 9px #222222",
        "gray2": "inset 0px 0px 0px 4.5px #9B9B9B,inset 0px 0px 0px 9px #222222",
        "inverted": "inset 0px 0px 0px 4.5px #FFFFFF,inset 0px 0px 0px 9px #222222",
        "hover": {
          "default": "inset 0px 0px 0px 4.5px #363636,inset 0px 0px 0px 9px #FFFFFF",
          "green": "inset 0px 0px 0px 4.5px #007A7A,inset 0px 0px 0px 9px #a2e8bd",
          "blue": "inset 0px 0px 0px 4.5px #0E7EC8,inset 0px 0px 0px 9px #9ee4ea",
          "red": "inset 0px 0px 0px 4.5px #B33225,inset 0px 0px 0px 9px #ffaaa2",
          "yellow": "inset 0px 0px 0px 4.5px #d3770d,inset 0px 0px 0px 9px #fff7cc",
          "magenta": "inset 0px 0px 0px 4.5px #A20065,inset 0px 0px 0px 9px #ffe0ed",
          "gray1": "inset 0px 0px 0px 4.5px {base.gray.4000},inset 0px 0px 0px 9px #222222",
          "gray2": "inset 0px 0px 0px 4.5px {base.gray.5500},inset 0px 0px 0px 9px #222222",
          "inverted": "inset 0px 0px 0px 4.5px #222222,inset 0px 0px 0px 9px #222222"
        }
      }
    }
  },
  "fontSizes": {
    "fontSizes": {
      "1": "16px",
      "2": "24px",
      "3": "36px",
      "4": "54px",
      "5": "81px",
      "6": "121.5px",
      "7": "182.25px"
    }
  },
  "fontFamilies": {
    "fontFamilies": {
      "Oleo": "Oleo Script",
      "Ubuntu": "Ubuntu"
    }
  },
  "fontWeights": {
    "fontWeights": {
      "regular": "Regular",
      "bold": "Bold"
    }
  },
  "lineHeights": {
    "lineheight": {
      "1": "66.66666666666667%",
      "2": "100%",
      "3": "150%"
    }
  },
  "spacing": {
    "spacing": {
      "1": "1rem",
      "2": "1.5rem",
      "3": "2.25rem",
      "4": "3.375rem",
      "5": "5.0625rem",
      "6": "7.59375rem",
      "7": "11.390625rem"
    }
  }
}